voice_commands/__init__.py
voice_commands/assistant.py
voice_commands/config.py
voice_commands/model_manager.py
voice_commands/types.py
voice_commands/core/__init__.py
voice_commands/core/audio_api.py
voice_commands/core/audio_processing_utils.py
voice_commands/core/executor.py
voice_commands/core/interpretation.py
voice_commands/core/recognition.py
voice_commands/core/voice_activity_detection.py
voice_commands-0.0.1.dist-info/METADATA
voice_commands-0.0.1.dist-info/WHEEL
voice_commands-0.0.1.dist-info/licenses/LICENSE
voice_commands-0.0.1.dist-info/RECORD
