Metadata-Version: 2.1
Name: voice_commands
Version: 0.0.1
Summary: Allows mapping commands to your voice
Project-URL: Homepage, https://github.com/Pizza989/voice_commands
Project-URL: Issues, https://github.com/Pizza989/voice_commands/issues
Author-email: Noah Simai <noah@simai.de>
License-File: LICENSE
Classifier: License :: OSI Approved :: Apache Software License
Classifier: Operating System :: POSIX :: Linux
Classifier: Programming Language :: Python :: 3
Requires-Python: >=3.11
Requires-Dist: numpy>=1.26.1
Requires-Dist: pyaudio>=0.2.11
Requires-Dist: tqdm>=4.66.1
Requires-Dist: vosk>=0.3.45
